tsbot/__init__.py
tsbot/bot.py
tsbot/context.py
tsbot/encoders.py
tsbot/enums.py
tsbot/exceptions.py
tsbot/logging.py
tsbot/parsers.py
tsbot/plugin.py
tsbot/py.typed
tsbot/ratelimiter.py
tsbot/response.py
tsbot/utils.py
tsbot/commands/__init__.py
tsbot/commands/command.py
tsbot/commands/manager.py
tsbot/connection/__init__.py
tsbot/connection/connection.py
tsbot/connection/reader.py
tsbot/connection/writer.py
tsbot/connection/connection_types/__init__.py
tsbot/connection/connection_types/abc.py
tsbot/connection/connection_types/raw_connection.py
tsbot/connection/connection_types/ssh_connection.py
tsbot/default_plugins/__init__.py
tsbot/default_plugins/default_plugins.py
tsbot/default_plugins/help.py
tsbot/default_plugins/keepalive.py
tsbot/events/__init__.py
tsbot/events/event.py
tsbot/events/event_handler.py
tsbot/events/event_types.py
tsbot/events/manager.py
tsbot/query_builder/__init__.py
tsbot/query_builder/builder.py
tsbot/query_builder/commands.py
tsbot/tasks/__init__.py
tsbot/tasks/manager.py
tsbot/tasks/task.py
tsbot-1.7.1.dist-info/licenses/LICENSE
tsbot-1.7.1.dist-info/METADATA
tsbot-1.7.1.dist-info/WHEEL
tsbot-1.7.1.dist-info/top_level.txt
tsbot-1.7.1.dist-info/RECORD
