Metadata-Version: 2.4
Name: tsbot
Version: 1.7.1
Summary: Asynchronous Python framework to build TeamSpeak 3 Server Query bots
Author: jykob
License: MIT License
Project-URL: repository, https://github.com/jykob/tsbot
Project-URL: documentation, https://tsbot.readthedocs.io/
Classifier: Development Status :: 5 - Production/Stable
Classifier: Framework :: AsyncIO
Classifier: License :: OSI Approved :: MIT License
Classifier: Operating System :: OS Independent
Classifier: Programming Language :: Python :: 3
Classifier: Programming Language :: Python :: 3 :: Only
Classifier: Programming Language :: Python :: 3.10
Requires-Python: >=3.10
License-File: LICENSE
Requires-Dist: asyncssh>=2.17.0
Requires-Dist: tsformatter>=0.2.1
Requires-Dist: typing_extensions>=4.13.1
Provides-Extra: dev
Requires-Dist: ruff>=0.4.4; extra == "dev"
Requires-Dist: pyright>=1.1.362; extra == "dev"
Requires-Dist: sphinx-autobuild>=2024.4.16; extra == "dev"
Requires-Dist: python-dotenv>=1.0.1; extra == "dev"
Provides-Extra: tests
Requires-Dist: pytest==8.3.3; extra == "tests"
Requires-Dist: pytest-asyncio==0.24.0; extra == "tests"
Provides-Extra: docs
Requires-Dist: sphinx>=7.3.7; extra == "docs"
Requires-Dist: myst-parser>=2.0.0; extra == "docs"
Requires-Dist: sphinx_rtd_theme>=2.0.0; extra == "docs"
Dynamic: license-file
